openedx_events/__init__.py
openedx_events/apps.py
openedx_events/data.py
openedx_events/exceptions.py
openedx_events/tooling.py
openedx_events/utils.py
openedx_events/analytics/__init__.py
openedx_events/analytics/data.py
openedx_events/analytics/signals.py
openedx_events/content_authoring/__init__.py
openedx_events/content_authoring/data.py
openedx_events/content_authoring/signals.py
openedx_events/enterprise/__init__.py
openedx_events/enterprise/data.py
openedx_events/enterprise/signals.py
openedx_events/event_bus/__init__.py
openedx_events/event_bus/avro/__init__.py
openedx_events/event_bus/avro/custom_serializers.py
openedx_events/event_bus/avro/deserializer.py
openedx_events/event_bus/avro/schema.py
openedx_events/event_bus/avro/serializer.py
openedx_events/event_bus/avro/types.py
openedx_events/event_bus/avro/tests/__init__.py
openedx_events/event_bus/avro/tests/test_avro.py
openedx_events/event_bus/avro/tests/test_custom_serializers.py
openedx_events/event_bus/avro/tests/test_deserializer.py
openedx_events/event_bus/avro/tests/test_schema.py
openedx_events/event_bus/avro/tests/test_serializer.py
openedx_events/event_bus/avro/tests/test_utilities.py
openedx_events/event_bus/tests/test_loader.py
openedx_events/learning/__init__.py
openedx_events/learning/data.py
openedx_events/learning/signals.py
openedx_events/management/__init__.py
openedx_events/management/commands/__init__.py
openedx_events/management/commands/consume_events.py
openedx_events/management/commands/generate_avro_schemas.py
openedx_events/tests/__init__.py
openedx_events/tests/test_consume_events_command.py
openedx_events/tests/test_data.py
openedx_events/tests/test_generate_avro_schemas.py
openedx_events/tests/test_producer_config.py
openedx_events/tests/test_tooling.py
openedx_events/tests/utils.py
openedx_events-10.5.0.dist-info/licenses/LICENSE.txt
openedx_events-10.5.0.dist-info/METADATA
openedx_events-10.5.0.dist-info/WHEEL
openedx_events-10.5.0.dist-info/top_level.txt
openedx_events-10.5.0.dist-info/RECORD
