Metadata-Version: 2.4
Name: openedx-events
Version: 10.5.0
Summary: Open edX events from the Hooks Extensions Framework
Home-page: https://github.com/openedx/openedx-events
Author: edX
Author-email: oscm@edx.org
License: Apache 2.0
Keywords: Python edx
Classifier: Development Status :: 3 - Alpha
Classifier: Intended Audience :: Developers
Classifier: License :: OSI Approved :: Apache Software License
Classifier: Natural Language :: English
Classifier: Programming Language :: Python :: 3
Classifier: Programming Language :: Python :: 3.11
Classifier: Programming Language :: Python :: 3.12
Requires-Python: >=3.11
License-File: LICENSE.txt
Requires-Dist: attrs
Requires-Dist: django
Requires-Dist: edx-ccx-keys
Requires-Dist: edx-opaque-keys[django]
Requires-Dist: edx_django_utils
Requires-Dist: fastavro
Requires-Dist: setuptools
Dynamic: author
Dynamic: author-email
Dynamic: classifier
Dynamic: description
Dynamic: description-content-type
Dynamic: home-page
Dynamic: keywords
Dynamic: license
Dynamic: license-file
Dynamic: requires-dist
Dynamic: requires-python
Dynamic: summary
